gpmaster/__init__.py
gpmaster/cli.py
gpmaster/format.py
gpmaster/gpg_ops.py
gpmaster/lockbox.py
gpmaster-1.1.2.dist-info/licenses/LICENSE
gpmaster-1.1.2.dist-info/METADATA
gpmaster-1.1.2.dist-info/WHEEL
gpmaster-1.1.2.dist-info/entry_points.txt
gpmaster-1.1.2.dist-info/top_level.txt
gpmaster-1.1.2.dist-info/RECORD
