Metadata-Version: 2.4
Name: gpmaster
Version: 1.1.2
Summary: GPG-backed lockbox for secrets management
Author: GPMaster Contributors
License: MIT
Project-URL: Homepage, https://github.com/yourusername/gpmaster
Project-URL: Repository, https://github.com/yourusername/gpmaster
Classifier: Development Status :: 4 - Beta
Classifier: Intended Audience :: Developers
Classifier: Intended Audience :: System Administrators
Classifier: License :: OSI Approved :: MIT License
Classifier: Programming Language :: Python :: 3
Classifier: Programming Language :: Python :: 3.8
Classifier: Programming Language :: Python :: 3.9
Classifier: Programming Language :: Python :: 3.10
Classifier: Programming Language :: Python :: 3.11
Classifier: Programming Language :: Python :: 3.12
Classifier: Topic :: Security
Classifier: Topic :: Security :: Cryptography
Requires-Python: >=3.8
License-File: LICENSE
Requires-Dist: python-gnupg>=0.5.0
Requires-Dist: pyotp>=2.8.0
Dynamic: license-file
Dynamic: requires-python
